adiff/__init__.py
adiff/cli.py
adiff-2.0.1.dist-info/METADATA
adiff-2.0.1.dist-info/WHEEL
adiff-2.0.1.dist-info/entry_points.txt
adiff-2.0.1.dist-info/top_level.txt
adiff-2.0.1.dist-info/RECORD
